docs/index.html
just_sh/__init__.py
just_sh/__main__.py
just_sh/convert.py
just_sh/parse.py
just_sh/py.typed
test/test.py
just.sh-0.0.2.dist-info/LICENSE
just.sh-0.0.2.dist-info/METADATA
just.sh-0.0.2.dist-info/WHEEL
just.sh-0.0.2.dist-info/entry_points.txt
just.sh-0.0.2.dist-info/top_level.txt
just.sh-0.0.2.dist-info/RECORD
