Metadata-Version: 2.1
Name: just.sh
Version: 0.0.2
Summary: Compile Justfiles to portable shell scripts
Author-email: Jacob Strieb <jstrieb@alumni.cmu.edu>
License: GNU GENERAL PUBLIC LICENSE
Project-URL: Homepage, https://github.com/jstrieb/just.sh
Project-URL: Repository, https://github.com/jstrieb/just.sh.git
Project-URL: Issues, https://github.com/jstrieb/just.sh/issues
Keywords: just,justfile,just.sh,shell,compiler,POSIX,pyjust
Classifier: Development Status :: 4 - Beta
Classifier: Environment :: Console
Classifier: Intended Audience :: Developers
Classifier: License :: OSI Approved :: GNU General Public License v3 (GPLv3)
Classifier: Operating System :: OS Independent
Classifier: Programming Language :: Python :: 3
Classifier: Topic :: Software Development
Classifier: Topic :: Software Development :: Code Generators
Classifier: Topic :: Software Development :: Build Tools
Classifier: Topic :: Utilities
Classifier: Typing :: Typed
Requires-Python: >=3.7
License-File: LICENSE
Requires-Dist: parsy >=2.1
Requires-Dist: importlib-metadata >=1.4 ; python_version < "3.8"
Provides-Extra: test
Requires-Dist: black >=23.3.0 ; extra == 'test'
Requires-Dist: mypy >=1.4.1 ; extra == 'test'
Requires-Dist: ruff >=0.1.8 ; extra == 'test'
Requires-Dist: pytest >=7.4.3 ; extra == 'test'
Requires-Dist: coverage[toml] >=6.5.0 ; extra == 'test'
Requires-Dist: pytest-cov >=4.1.0 ; extra == 'test'
Requires-Dist: pytest-xdist >=3.5.0 ; extra == 'test'
